MANIFEST.in
README.txt
setup.cfg
setup.py
bin/python-jquery
jsjquery/__init__.py
jsjquery.egg-info/PKG-INFO
jsjquery.egg-info/SOURCES.txt
jsjquery.egg-info/dependency_links.txt
jsjquery.egg-info/not-zip-safe
jsjquery.egg-info/top_level.txt