Metadata-Version: 1.0
Name: jsjquery
Version: 1.3.2
Summary: Install and list jQuery as a dependency via PyPI.
Home-page: http://www.jquery.com
Author: Ask Solem
Author-email: askh@opera.com
License: UNKNOWN
Platform: UNKNOWN
Classifier: Development Status :: 3 - Alpha
Classifier: Intended Audience :: Developers
Classifier: License :: OSI Approved :: GNU General Public License (GPL)
Classifier: Operating System :: OS Independent
Classifier: Programming Language :: JavaScript
